PyCloudSim/__init__.py
PyCloudSim/entity/__init__.py
PyCloudSim/entity/constants.py
PyCloudSim/entity/v_apicall.py
PyCloudSim/entity/v_container.py
PyCloudSim/entity/v_cpu.py
PyCloudSim/entity/v_cpu_core.py
PyCloudSim/entity/v_gateway.py
PyCloudSim/entity/v_hardware_component.py
PyCloudSim/entity/v_hardware_entity.py
PyCloudSim/entity/v_host.py
PyCloudSim/entity/v_instruction.py
PyCloudSim/entity/v_microservice.py
PyCloudSim/entity/v_nic.py
PyCloudSim/entity/v_packet.py
PyCloudSim/entity/v_process.py
PyCloudSim/entity/v_router.py
PyCloudSim/entity/v_sfc.py
PyCloudSim/entity/v_sofware_entity.py
PyCloudSim/entity/v_switch.py
PyCloudSim/entity/v_user.py
PyCloudSim/entity/v_volume.py
PyCloudSim/monitor/__init__.py
PyCloudSim/monitor/container_monitor.py
PyCloudSim/monitor/host_monitor.py
PyCloudSim/monitor/microservice_monitor.py
PyCloudSim/scheduler/__init__.py
PyCloudSim/scheduler/container_scheduler.py
PyCloudSim/scheduler/volume_scheduler.py
PyCloudSim-1.0.7.dist-info/LICENSE-CC-BY-NC-ND-4.0.md
PyCloudSim-1.0.7.dist-info/METADATA
PyCloudSim-1.0.7.dist-info/WHEEL
PyCloudSim-1.0.7.dist-info/top_level.txt
PyCloudSim-1.0.7.dist-info/RECORD
