Metadata-Version: 2.2
Name: PyCloudSim
Version: 1.0.7
Summary: A small example package
Author-email: Yifei Ren <ryf0510@live.com>
Project-URL: Homepage, https://ulfaric.github.io/PyCloudSim/
Project-URL: Bug Tracker, https://ulfaric.github.io/PyCloudSim/issues
Classifier: Programming Language :: Python :: 3
Classifier: License :: OSI Approved :: MIT License
Classifier: Operating System :: OS Independent
Requires-Python: >=3.7
License-File: LICENSE-CC-BY-NC-ND-4.0.md
Requires-Dist: bitmath
Requires-Dist: networkx
Requires-Dist: Akatosh<=2.3.3
